text_parsematch/__init__.py
text_parsematch/main.py
text_parsematch/prompts.py
text_parsematch-2025.12.22111249.dist-info/METADATA
text_parsematch-2025.12.22111249.dist-info/WHEEL
text_parsematch-2025.12.22111249.dist-info/top_level.txt
text_parsematch-2025.12.22111249.dist-info/RECORD
