Metadata-Version: 2.4
Name: text-parsematch
Version: 2025.12.22111249
Summary: text-parsematch processes text input with pattern matching and retries to ensure structured, validated output for data extraction and content categorization.
Author-email: text-parsematch <hi@eugene.plus>
License: MIT
Project-URL: Homepage, https://github.com/chigwell/text-parsematch
Requires-Python: >=3.9
Requires-Dist: langchain-llm7>=0.0.0
Requires-Dist: llmatch-messages>=0.0.0
Requires-Dist: langchain-core>=0.3.0
